{
  "display": {
    "icon": {
      "item": "buildcraftcore:gear_wood"
    },
    "title": {
      "translate": "advancements.buildcraftcore.root.title"
    },
    "description": {
      "translate": "advancements.buildcraftcore.root.description"
    },
    "background": "minecraft:textures/gui/advancements/backgrounds/adventure.png",
    "show_toast": false,
    "announce_to_chat": false
  },
  "criteria": {
    "has_stick": {
      "trigger": "minecraft:inventory_changed",
      "conditions": {
        "items": [
          {
            "item": "minecraft:stick"
          }
        ]
      }
    }
  },
  "rewards": {
    "recipes": [
      "buildcraftcore:gear_wood"
    ]
  }
}